kubiat/DBconn.py
kubiat/__init__.py
kubiat/events.py
kubiat/mongodb.py
kubiat/service.py
kubiat/tool.py
kubiat-0.1.2.dist-info/LICENSE
kubiat-0.1.2.dist-info/METADATA
kubiat-0.1.2.dist-info/WHEEL
kubiat-0.1.2.dist-info/top_level.txt
kubiat-0.1.2.dist-info/RECORD
