Metadata-Version: 2.1
Name: kubiat
Version: 0.1.2
Summary: Base python support package for python
Home-page: https://example.com
Author: Mark
Author-email: mark@example.com
License: UNKNOWN
Project-URL: Docs, https://docs.example.com
Platform: UNKNOWN
Classifier: Programming Language :: Python :: 3
Classifier: License :: OSI Approved :: MIT License
Classifier: Operating System :: OS Independent
Requires-Python: >=3.6
License-File: LICENSE
Requires-Dist: pymongo
Requires-Dist: cloudevents
Requires-Dist: requests
Requires-Dist: Flask
Requires-Dist: gunicorn
Requires-Dist: flask-cors
